vformer/__init__.py
vformer/attention/__init__.py
vformer/attention/convvt.py
vformer/attention/cross.py
vformer/attention/gated_positional.py
vformer/attention/memory_efficient.py
vformer/attention/spatial.py
vformer/attention/vanilla.py
vformer/attention/window.py
vformer/common/__init__.py
vformer/common/base_model.py
vformer/common/base_trainer.py
vformer/common/blocks.py
vformer/decoder/__init__.py
vformer/decoder/mlp.py
vformer/decoder/perceiver_io.py
vformer/decoder/task_heads/__init__.py
vformer/decoder/task_heads/detection/__init__.py
vformer/decoder/task_heads/detection/head.py
vformer/decoder/task_heads/segmentation/__init__.py
vformer/decoder/task_heads/segmentation/head.py
vformer/encoder/__init__.py
vformer/encoder/convit.py
vformer/encoder/convvt.py
vformer/encoder/cross.py
vformer/encoder/nn.py
vformer/encoder/perceiver_io.py
vformer/encoder/pyramid.py
vformer/encoder/swin.py
vformer/encoder/vanilla.py
vformer/encoder/vivit.py
vformer/encoder/embedding/__init__.py
vformer/encoder/embedding/convvt.py
vformer/encoder/embedding/cvt.py
vformer/encoder/embedding/linear.py
vformer/encoder/embedding/overlappatch.py
vformer/encoder/embedding/patch.py
vformer/encoder/embedding/pos_embedding.py
vformer/encoder/embedding/video_patch_embeddings.py
vformer/functional/__init__.py
vformer/functional/merge.py
vformer/functional/norm.py
vformer/models/__init__.py
vformer/models/classification/__init__.py
vformer/models/classification/cct.py
vformer/models/classification/convit.py
vformer/models/classification/convvt.py
vformer/models/classification/cross.py
vformer/models/classification/cvt.py
vformer/models/classification/perceiver_io.py
vformer/models/classification/pyramid.py
vformer/models/classification/swin.py
vformer/models/classification/vanilla.py
vformer/models/classification/visformer.py
vformer/models/classification/vivit.py
vformer/models/dense/__init__.py
vformer/models/dense/dpt.py
vformer/models/dense/PVT/__init__.py
vformer-0.1.3.dist-info/AUTHORS.rst
vformer-0.1.3.dist-info/LICENSE
vformer-0.1.3.dist-info/METADATA
vformer-0.1.3.dist-info/WHEEL
vformer-0.1.3.dist-info/top_level.txt
vformer-0.1.3.dist-info/RECORD
