Metadata-Version: 2.1
Name: vformer
Version: 0.1.3
Summary: A modular PyTorch library for vision transformer models
Home-page: https://github.com/SforAiDl/vformer
Author: Neelay Shah
Author-email: nstraum1@gmail.com
License: MIT
Project-URL: Source, https://github.com/SforAiDl/vformer
Keywords: vision transformers,pytorch,computer vision,machine learning,deep learning
Classifier: Development Status :: 2 - Pre-Alpha
Classifier: Intended Audience :: Developers
Classifier: License :: OSI Approved :: MIT License
Classifier: Natural Language :: English
Classifier: Programming Language :: Python :: 3
Classifier: Programming Language :: Python :: 3.6
Classifier: Programming Language :: Python :: 3.7
Classifier: Programming Language :: Python :: 3.8
Requires-Python: >=3.6
License-File: LICENSE
License-File: AUTHORS.rst
Requires-Dist: arrow (==1.1.1)
Requires-Dist: attrs (==21.2.0)
Requires-Dist: backports.entry-points-selectable (==1.1.0)
Requires-Dist: binaryornot (==0.4.4)
Requires-Dist: certifi (==2021.5.30)
Requires-Dist: cfgv (==3.3.1)
Requires-Dist: chardet (==4.0.0)
Requires-Dist: charset-normalizer (==2.0.4)
Requires-Dist: click (==8.0.1)
Requires-Dist: cookiecutter (==1.7.3)
Requires-Dist: distlib (==0.3.2)
Requires-Dist: einops (==0.3.2)
Requires-Dist: filelock (==3.0.12)
Requires-Dist: identify (==2.2.13)
Requires-Dist: idna (==3.2)
Requires-Dist: iniconfig (==1.1.1)
Requires-Dist: Jinja2 (==3.0.1)
Requires-Dist: jinja2-time (==0.2.0)
Requires-Dist: MarkupSafe (==2.0.1)
Requires-Dist: nodeenv (==1.6.0)
Requires-Dist: olefile
Requires-Dist: packaging (==21.0)
Requires-Dist: Pillow
Requires-Dist: platformdirs (==2.3.0)
Requires-Dist: pluggy (==1.0.0)
Requires-Dist: poyo (==0.5.0)
Requires-Dist: pre-commit (==2.15.0)
Requires-Dist: py (==1.10.0)
Requires-Dist: pyparsing (==2.4.7)
Requires-Dist: pytest (>=6.2.5)
Requires-Dist: python-dateutil (==2.8.2)
Requires-Dist: python-slugify (==5.0.2)
Requires-Dist: PyYAML (==5.4.1)
Requires-Dist: requests (==2.26.0)
Requires-Dist: six (==1.16.0)
Requires-Dist: text-unidecode (==1.3)
Requires-Dist: toml (==0.10.2)
Requires-Dist: torch (>=1.10.0)
Requires-Dist: torchvision (>=0.11.0)
Requires-Dist: typing-extensions
Requires-Dist: urllib3 (==1.26.6)
Requires-Dist: virtualenv (==20.7.2)
